pyimagediet/__init__.py
pyimagediet/diet.py
pyimagediet-0.5.dist-info/DESCRIPTION.rst
pyimagediet-0.5.dist-info/METADATA
pyimagediet-0.5.dist-info/metadata.json
pyimagediet-0.5.dist-info/RECORD
pyimagediet-0.5.dist-info/top_level.txt
pyimagediet-0.5.dist-info/WHEEL
